clarifai_evals/__init__.py
clarifai_evals/common_base_evaluator.py
clarifai_evals/constant.py
clarifai_evals/result_data.py
clarifai_evals/evaluators/workflow_evaluator.py
clarifai_evals/image_eval/__init__.py
clarifai_evals/image_eval/base_eval.py
clarifai_evals/image_eval/image_utils.py
clarifai_evals/image_eval/image_detection_eval/__init__.py
clarifai_evals/image_eval/image_detection_eval/detection_evaluator.py
clarifai_evals/image_eval/image_detection_eval/eval_with_gt/__init__.py
clarifai_evals/image_eval/image_detection_eval/eval_with_gt/evaluate.py
clarifai_evals/image_eval/image_segmentation_eval/__init__.py
clarifai_evals/image_eval/image_segmentation_eval/image_segmentation_evaluator.py
clarifai_evals/image_eval/image_segmentation_eval/utils.py
clarifai_evals/image_eval/image_segmentation_eval/eval_with_gt/__init__.py
clarifai_evals/image_eval/image_segmentation_eval/eval_with_gt/evaluate.py
clarifai_evals/image_eval/ocr_eval/__init__.py
clarifai_evals/image_eval/ocr_eval/ocr_evaluator.py
clarifai_evals/image_eval/ocr_eval/eval_with_gt/__init__.py
clarifai_evals/image_eval/ocr_eval/eval_with_gt/evaluate.py
clarifai_evals/text_eval/__init__.py
clarifai_evals/text_eval/base_eval.py
clarifai_evals/text_eval/prompt_templates.py
clarifai_evals/text_eval/utils.py
clarifai_evals/text_eval/text_classification_eval/__init__.py
clarifai_evals/text_eval/text_classification_eval/classification_evaluator.py
clarifai_evals/text_eval/text_classification_eval/eval_with_gt/__init__.py
clarifai_evals/text_eval/text_classification_eval/eval_with_gt/evaluate.py
clarifai_evals/text_eval/text_classification_eval/eval_with_llm_as_judge/__init__.py
clarifai_evals/text_eval/text_classification_eval/eval_with_llm_as_judge/evaluate.py
clarifai_evals/text_eval/text_generation_eval/__init__.py
clarifai_evals/text_eval/text_generation_eval/base_text_gen_eval.py
clarifai_evals/text_eval/text_generation_eval/text_gen_evaluator.py
clarifai_evals-0.1.0a10.dist-info/LICENSE
clarifai_evals-0.1.0a10.dist-info/METADATA
clarifai_evals-0.1.0a10.dist-info/WHEEL
clarifai_evals-0.1.0a10.dist-info/top_level.txt
clarifai_evals-0.1.0a10.dist-info/RECORD
