Metadata-Version: 2.1
Name: clarifai-evals
Version: 0.1.0a10
Summary: Clarifai Evals is an SDK for evaluating AI models, providing a structured framework to benchmark model performance using predefined and custom evaluation templates.
Home-page: https://github.com/Clarifai/clarifai-evals
Author: Clarifai
Author-email: support@clarifai.com
License: Apache 2.0
Classifier: Topic :: Scientific/Engineering :: Artificial Intelligence
Classifier: Programming Language :: Python :: 3
Classifier: Programming Language :: Python :: 3 :: Only
Classifier: Programming Language :: Python :: 3.9
Classifier: Programming Language :: Python :: 3.10
Classifier: Programming Language :: Python :: 3.11
Classifier: Programming Language :: Python :: 3.12
Classifier: Programming Language :: Python :: Implementation :: CPython
Classifier: License :: OSI Approved :: Apache Software License
Classifier: Operating System :: OS Independent
Requires-Python: >=3.9
License-File: LICENSE
Requires-Dist: clarifai==11.6.0
Requires-Dist: clarifai-grpc>=11.2.0
Requires-Dist: numpy
Requires-Dist: scikit-learn
Requires-Dist: opencv-python-headless
Requires-Dist: pillow
Requires-Dist: fiftyone
Requires-Dist: opencv-python
Requires-Dist: jiwer==3.1.0
Requires-Dist: joblib==1.4.2
